talk/__init__.py
talk/bar.py
talk_cloud-0.0.1.dist-info/LICENSE
talk_cloud-0.0.1.dist-info/METADATA
talk_cloud-0.0.1.dist-info/WHEEL
talk_cloud-0.0.1.dist-info/top_level.txt
talk_cloud-0.0.1.dist-info/RECORD
