Metadata-Version: 2.1
Name: talk-cloud
Version: 0.0.1
Summary: Talk-Cloud SDK for Python
Home-page: https://github.com/ni-ning/talk-cloud
Author: lightnning
Author-email: nining1314@gmail.com
License: UNKNOWN
Keywords: talk-cloud,sdk
Platform: UNKNOWN
Classifier: Development Status :: 3 - Alpha
Classifier: Intended Audience :: Developers
Classifier: Topic :: Software Development :: Build Tools
Classifier: License :: OSI Approved :: MIT License
Classifier: Programming Language :: Python :: 2
Classifier: Programming Language :: Python :: 2.7
Classifier: Programming Language :: Python :: 3
Classifier: Programming Language :: Python :: 3.3
Classifier: Programming Language :: Python :: 3.4
Classifier: Programming Language :: Python :: 3.5
Classifier: Programming Language :: Python :: 3.6
Classifier: Programming Language :: Python :: 3.7
Requires-Dist: six (>=1.8.0)
Requires-Dist: requests (>=2.4.3)
